king_libs/CM.py
king_libs/__init__.py
king_libs/currency.py
king_libs/ip.py
king_libs/kip.py
king_libs/picTotext.py
king_libs/shutdown.py
king_libs/sort_val.py
king_libs/king_tools/__init__.py
king_libs/king_tools/functions.py
king_libs/king_tools/stop_words.py
king_libs/number_to_word_project/__init__.py
king_libs/number_to_word_project/basic_number.py
king_libs/number_to_word_project/main_detect.py
king_libs/number_to_word_project/milion.py
king_libs/number_to_word_project/miliyard.py
king_libs/number_to_word_project/num_to_alphabic.py
king_libs/number_to_word_project/sadhezar.py
king_libs-0.0.8.dist-info/LICENSE
king_libs-0.0.8.dist-info/LICENSE.txt
king_libs-0.0.8.dist-info/METADATA
king_libs-0.0.8.dist-info/WHEEL
king_libs-0.0.8.dist-info/top_level.txt
king_libs-0.0.8.dist-info/RECORD
