Metadata-Version: 2.1
Name: king-libs
Version: 0.0.8
Summary: This is code with king package
Home-page: https://github.com/jacktamin/king_libs
Author: Ahmad Dehghani
Author-email: ahd76money@gmail.com
License: MIT
Download-URL: https://github.com/jacktamin/king_libs/king_libs-0.0.6.tar.gz
Keywords: scraping,easy,scraper,website,download,links,images,videos
Platform: UNKNOWN
